simanager/__init__.py
simanager/cli_tools.py
simanager/copy_template.py
simanager/job_run_htcondor.py
simanager/job_run_local.py
simanager/job_run_slurm.py
simanager/parameter_inspection.py
simanager/simulation_study.py
simanager/tools.py
simanager/templates/create_folders.sh
simanager/templates/reset_all.sh
simanager/templates/reset_broken.sh
simanager/templates/run_config.yaml
simanager/templates/simulation_study.yaml
simanager/templates/master_study/main_script.sh
simanager/templates/master_study/params.yaml
simanager/templates/master_study/script.py
simanager-0.0.4.dist-info/LICENSE
simanager-0.0.4.dist-info/METADATA
simanager-0.0.4.dist-info/WHEEL
simanager-0.0.4.dist-info/entry_points.txt
simanager-0.0.4.dist-info/top_level.txt
simanager-0.0.4.dist-info/RECORD
