Metadata-Version: 2.1
Name: simanager
Version: 0.0.4
Summary: A Python package for managing simulations locally, on HTCondor and on Slurm, with some specific elements that are good in a CERNy environment.
Home-page: https://github.com/carlidel/simanager
Author: Carlo Emilio Montanari
Author-email: carlo.emilio.montanari@cern.ch
License: MIT
License-File: LICENSE
Requires-Dist: numpy
Requires-Dist: pyyaml
